path_name_parser/__init__.py
path_name_parser/path_name_parser.py
path_name_parser/pattern_matcher.py
path_name_parser-0.1.4.dist-info/LICENSE
path_name_parser-0.1.4.dist-info/METADATA
path_name_parser-0.1.4.dist-info/WHEEL
path_name_parser-0.1.4.dist-info/RECORD
