Metadata-Version: 2.3
Name: path_name_parser
Version: 0.1.4
Summary: Universal, extensible Python library for extracting structured information (groups, dates, times, custom patterns) from file names and paths.
License: MIT
Author: Oleg migutin83@yandex.ru
Requires-Python: >=3.8,<4.0
Classifier: License :: OSI Approved :: MIT License
Classifier: Programming Language :: Python :: 3
Classifier: Programming Language :: Python :: 3.8
Classifier: Programming Language :: Python :: 3.9
Classifier: Programming Language :: Python :: 3.10
Classifier: Programming Language :: Python :: 3.11
Classifier: Programming Language :: Python :: 3.12
Classifier: Programming Language :: Python :: 3.13
Project-URL: Homepage, https://github.com/migutin83/path_name_parser
Project-URL: Issues, https://github.com/migutin83/path_name_parser/issues
